README.rst
setup.py
ttrss/__init__.py
ttrss/auth.py
ttrss/client.py
ttrss/exceptions.py
ttrss_python.egg-info/PKG-INFO
ttrss_python.egg-info/SOURCES.txt
ttrss_python.egg-info/dependency_links.txt
ttrss_python.egg-info/requires.txt
ttrss_python.egg-info/top_level.txt