Metadata-Version: 1.1
Name: ttrss-python
Version: 0.5
Summary: A client library for the Tiny Tiny RSS web API
Home-page: https://github.com/Vassius/ttrss-python
Author: Markus Wiik
Author-email: vassius@gmail.com
License: UNKNOWN
Platform: UNKNOWN
Classifier: Development Status :: 4 - Beta
Classifier: Intended Audience :: Developers
Classifier: Intended Audience :: System Administrators
Classifier: License :: OSI Approved :: MIT License
Classifier: Operating System :: OS Independent
Classifier: Programming Language :: Python :: 2.7
Classifier: Topic :: Internet :: WWW/HTTP
Provides: ttrss
